{"dependencies":[{"name":"./style.css","dynamic":true},{"name":"./img\\1.png","dynamic":true},{"name":"./img\\2.png","dynamic":true},{"name":"./img\\3.png","dynamic":true},{"name":"./img\\4.png","dynamic":true},{"name":"./img\\5.png","dynamic":true},{"name":"./img\\6.png","dynamic":true},{"name":"./img\\7.png","dynamic":true},{"name":"./img\\8.png","dynamic":true},{"name":"./img\\9.png","dynamic":true},{"name":"./img\\10.png","dynamic":true},{"name":"./img\\11.png","dynamic":true},{"name":"./img\\12.png","dynamic":true},{"name":"./img\\13.png","dynamic":true},{"name":"./img\\14.png","dynamic":true},{"name":"./img\\15.png","dynamic":true},{"name":"./img\\16.png","dynamic":true},{"name":"./main.js","dynamic":true}],"generated":{"html":"<!doctype html>\r\n<html lang=\"zh-CN\">\r\n<head>\r\n    <meta charset=\"UTF-8\">\r\n    <meta name=\"viewport\" content=\"width=device-width, user-scalable=no, initial-scale=1.0, maximum-scale=1.0, minimum-scale=1.0\">\r\n    <meta http-equiv=\"X-UA-Compatible\" content=\"ie=edge\">\r\n    <title>哔哩哔哩 (゜-゜)つロ 干杯~-bilibili</title>\r\n    <link rel=\"stylesheet\" href=\"/400d72c12fdfeffcd56629ff39c2aaab.css\">\r\n\r\n</head>\r\n<body>\r\n<div id=\"app\">\r\n    <div class=\"international-home\">\r\n        <div id=\"internationalHeader\" class=\"international-header report-wrap-module\">\r\n            <div class=\"bili-banner\" style=\"\" data-v-cd8268ae=\"\">\r\n                <div data-v-66241fcf=\"\" data-v-cd8268ae=\"\" class=\"animated-banner\">\r\n                    <div class=\"layer\"><img src=\"/209930e6ce2e13bb7bfb69c8c98afe66.png\" data-height=\"360\" data-width=\"9666\" height=\"180\" width=\"4833\" style=\"transform: scale(1) translate(0px, -15px) rotate(0deg); opacity: 1;\"></div>\r\n                    <div class=\"layer\"><img src=\"/e15f80e3056c7ef1e54aafdfcfc34e51.png\" data-height=\"360\" data-width=\"9666\" height=\"180\" width=\"4833\" style=\"transform: scale(1) translate(1100px, 0px) rotate(0deg); opacity: 1;\"></div>\r\n                    <div class=\"layer\"><img src=\"/6a9d6ef55874295cabc566c3407021d5.png\" data-height=\"360\" data-width=\"3523\" height=\"162\" width=\"1585\" style=\"transform: scale(1) translate(675px, 0px) rotate(0deg); opacity: 1;\"></div>\r\n                    <div class=\"layer\"><img src=\"/5652cf0edaa2765b3b8a7d11c2685803.png\" data-height=\"360\" data-width=\"2938\" height=\"176\" width=\"1439\" style=\"transform: scale(1) translate(-637px, 0px) rotate(0deg); opacity: 1;\"></div>\r\n                    <div class=\"layer\"><img src=\"/4eabac33928b73a24ee009653f1a9920.png\" data-height=\"139\" data-width=\"556\" height=\"62\" width=\"250\" style=\"transform: scale(1) translate(607.5px, 45px) rotate(0deg); opacity: 1;\"></div>\r\n                    <div class=\"layer\"><img src=\"/0bd0f748ae0b9d8629c84d2ef7da3a56.png\" data-height=\"302\" data-width=\"734\" height=\"84\" width=\"205\" style=\"transform: scale(1) translate(252px, 36.4px) rotate(0deg); opacity: 0;\"></div>\r\n                    <div class=\"layer\"><img src=\"/62b7259b79bc32360c8d5e693ab9a194.png\" data-height=\"180\" data-width=\"1757\" height=\"125\" width=\"1229\" style=\"transform: scale(1) translate(112px, 14px) rotate(0deg); opacity: 1;\"></div>\r\n                    <div class=\"layer\"><img src=\"/89c19f03352620f43a8edaf8bf2dc83e.png\" data-height=\"116\" data-width=\"1757\" height=\"81\" width=\"1229\" style=\"transform: scale(1) translate(-350px, 49px) rotate(0deg); opacity: 1;\"></div>\r\n                    <div class=\"layer\"><img src=\"/237d93b41139f5461b6c48a493df96df.png\" data-height=\"346\" data-width=\"497\" height=\"138\" width=\"198\" style=\"transform: scale(1) translate(-240px, 16px) rotate(0deg); opacity: 0;\"></div>\r\n                    <div class=\"layer\"><img src=\"/a95bebf638fe119905d6db3c354a4efc.png\" data-height=\"256\" data-width=\"146\" height=\"102\" width=\"58\" style=\"transform: scale(1) translate(-340px, 32px) rotate(0deg); opacity: 0;\"></div>\r\n                    <div class=\"layer\"><img src=\"/b2a7eb6999c71bac8f17be9196532f15.png\" data-height=\"254\" data-width=\"602\" height=\"114\" width=\"270\" style=\"transform: scale(1) translate(-90px, 13.5px) rotate(0deg); opacity: 1;\"></div>\r\n                    <div class=\"layer\"><img src=\"/6b36c04b846254f811eedc4e152d1d4e.png\" data-height=\"360\" data-width=\"4277\" height=\"180\" width=\"2138\" style=\"transform: scale(1) translate(100px, 0px) rotate(0deg); opacity: 1;\"></div>\r\n                    <div class=\"layer\"><img src=\"/1f68183a8589d52a9bc144430979d1e2.png\" data-height=\"327\" data-width=\"933\" height=\"147\" width=\"419\" style=\"transform: scale(1) translate(216px, 13.5px) rotate(0deg); opacity: 1;\"></div>\r\n                    <div class=\"layer\"><img src=\"/4f995d0a3d492aa4b0cee004be36509f.png\" data-height=\"353\" data-width=\"740\" height=\"211\" width=\"444\" style=\"transform: scale(1) translate(2100px, 0px) rotate(0deg); filter: blur(2px); opacity: 1;\">\r\n                    </div>\r\n                    <div class=\"layer\"><img src=\"/ff95d90228b0bbd198e87382fa15841e.png\" data-height=\"360\" data-width=\"1916\" height=\"180\" width=\"958\" style=\"transform: scale(1) translate(-1000px, 0px) rotate(0deg); filter: blur(1px); opacity: 1;\">\r\n                    </div>\r\n                    <canvas width=\"999\" height=\"155\" style=\"position: absolute; top: 0px; left: 0px;\"></canvas>\r\n                </div>\r\n                <div class=\"taper-line\" data-v-cd8268ae=\"\"></div>\r\n                <div class=\"b-logo b-wrap\" style=\"margin: 0\" data-v-cd8268ae=\"\"><a href=\"//www.bilibili.com\" class=\"head-logo\" data-v-cd8268ae=\"\"><img src=\"/8612d0d77ba714423ab3f6079e086223.png\" class=\"logo-img\" data-v-cd8268ae=\"\"></a><!----></div><!----></div>\r\n        </div>\r\n    </div>\r\n</div>\r\n    <script type=\"text/javascript\" src=\"/380c90764ddae85d5abe140183ea72cd.js\"></script>\r\n</body>\r\n</html>"},"hash":"b893e7fc2f56bc31fddec19e4eec6029","cacheData":{}}